versioning/__init__.py
versioning/hatchling.py
versioning/pep440.py
versioning/project.py
versioning/semver2.py
versioning/setuptools.py
versioning/version.py
simple_git_versioning-0.3.11.dist-info/METADATA
simple_git_versioning-0.3.11.dist-info/WHEEL
simple_git_versioning-0.3.11.dist-info/entry_points.txt
simple_git_versioning-0.3.11.dist-info/licenses/LICENSE
simple_git_versioning-0.3.11.dist-info/RECORD
