Metadata-Version: 2.4
Name: simple-git-versioning
Version: 0.3.11
Summary: Thinly scoped and opinionated tool that computes a version number from git tags and trailers
Project-URL: homepage, https://gitlab.com/ypsah/simple-git-versioning
Project-URL: repository, https://gitlab.com/ypsah/simple-git-versioning
Author-email: Quentin Bouget <ypsah@devyard.org>
License: MIT
License-File: LICENSE
Keywords: git,git-trailers,versioning
Classifier: Development Status :: 3 - Alpha
Classifier: Environment :: Console
Classifier: Framework :: Hatch
Classifier: Intended Audience :: Developers
Classifier: License :: OSI Approved :: MIT License
Classifier: Operating System :: OS Independent
Classifier: Programming Language :: Python
Classifier: Programming Language :: Python :: 3 :: Only
Classifier: Programming Language :: Python :: 3.8
Classifier: Programming Language :: Python :: 3.9
Classifier: Programming Language :: Python :: 3.10
Classifier: Programming Language :: Python :: 3.11
Classifier: Programming Language :: Python :: 3.12
Classifier: Programming Language :: Python :: 3.13
Requires-Python: <4,>=3.8.1
Requires-Dist: icontract
Requires-Dist: sh<3,>=2
Requires-Dist: toml; python_version < '3.11'
Requires-Dist: typing-extensions; python_version < '3.11'
Provides-Extra: hatchling
Requires-Dist: hatchling; extra == 'hatchling'
Provides-Extra: poetry
Requires-Dist: cleo; extra == 'poetry'
Requires-Dist: poetry; extra == 'poetry'
Provides-Extra: setuptools
Requires-Dist: setuptools; extra == 'setuptools'
